[
    {
        "key": "datr",
        "value": "Vrh8aUGW0Ul8wp11jfH7hLs4",
        "domain": "facebook.com",
        "path": "/",
        "hostOnly": false,
        "creation": "2026-02-12T20:58:36.611Z",
        "lastAccessed": "2026-02-12T20:58:36.611Z"
    },
    {
        "key": "sb",
        "value": "Vrh8aQAkqd9D5JZcV-uy1Mvd",
        "domain": "facebook.com",
        "path": "/",
        "hostOnly": false,
        "creation": "2026-02-12T20:58:36.611Z",
        "lastAccessed": "2026-02-12T20:58:36.611Z"
    },
    {
        "key": "ps_l",
        "value": "1",
        "domain": "facebook.com",
        "path": "/",
        "hostOnly": false,
        "creation": "2026-02-12T20:58:36.611Z",
        "lastAccessed": "2026-02-12T20:58:36.611Z"
    },
    {
        "key": "ps_n",
        "value": "1",
        "domain": "facebook.com",
        "path": "/",
        "hostOnly": false,
        "creation": "2026-02-12T20:58:36.611Z",
        "lastAccessed": "2026-02-12T20:58:36.611Z"
    },
    {
        "key": "dpr",
        "value": "2.214021682739258",
        "domain": "facebook.com",
        "path": "/",
        "hostOnly": false,
        "creation": "2026-02-12T20:58:36.611Z",
        "lastAccessed": "2026-02-12T20:58:36.611Z"
    },
    {
        "key": "wd",
        "value": "775x1459",
        "domain": "facebook.com",
        "path": "/",
        "hostOnly": false,
        "creation": "2026-02-12T20:58:36.611Z",
        "lastAccessed": "2026-02-12T20:58:36.611Z"
    },
    {
        "key": "c_user",
        "value": "61587626232790",
        "domain": "facebook.com",
        "path": "/",
        "hostOnly": false,
        "creation": "2026-02-12T20:58:36.611Z",
        "lastAccessed": "2026-02-12T20:58:36.611Z"
    },
    {
        "key": "fr",
        "value": "1e4tfAU8iNmpPzpOW.AWfScP3MMafu-CZqAtYnoos1AgnzF22vPCe1z-GsC9F-YiHFjV4.Bpjj7x..AAA.0.0.Bpjj7x.AWc6GlhAONXiQnjJ2iLd7AdsuhA",
        "domain": "facebook.com",
        "path": "/",
        "hostOnly": false,
        "creation": "2026-02-12T20:58:36.611Z",
        "lastAccessed": "2026-02-12T20:58:36.611Z"
    },
    {
        "key": "xs",
        "value": "49%3AkMu-4XKMsz_FjQ%3A2%3A1770929899%3A-1%3A-1%3A%3AAcz7buOb8Kf_44Ksu5CS4j18_qKFO4_0mIR65zGYsg",
        "domain": "facebook.com",
        "path": "/",
        "hostOnly": false,
        "creation": "2026-02-12T20:58:36.611Z",
        "lastAccessed": "2026-02-12T20:58:36.611Z"
    },
    {
        "key": "presence",
        "value": "C%7B%22t3%22%3A%5B%5D%2C%22utc3%22%3A1770929910765%2C%22v%22%3A1%7D",
        "domain": "facebook.com",
        "path": "/",
        "hostOnly": false,
        "creation": "2026-02-12T20:58:36.611Z",
        "lastAccessed": "2026-02-12T20:58:36.611Z"
    }
]
